nuvemshop_client/__init__.py
nuvemshop_client/client.py
nuvemshop_client/exception.py
nuvemshop_client/resources/__init__.py
nuvemshop_client/resources/abandoned_checkouts.py
nuvemshop_client/resources/base.py
nuvemshop_client/resources/customers.py
nuvemshop_client/resources/orders.py
nuvemshop_client/resources/products.py
nuvemshop_client/resources/stores.py
nuvemshop_client/resources/webhooks.py
tests/test_abandoned_chekouts.py
tests/test_client.py
tests/test_webhooks.py
nuvemshop_client_python-0.2.5.dist-info/METADATA
nuvemshop_client_python-0.2.5.dist-info/WHEEL
nuvemshop_client_python-0.2.5.dist-info/top_level.txt
nuvemshop_client_python-0.2.5.dist-info/RECORD
