Metadata-Version: 2.4
Name: nuvemshop-client-python
Version: 0.2.5
Summary: Um cliente Python robusto e intuitivo para a API da Nuvemshop.
Author-email: Bruno Vidal <brunovidal@lojabibelo.com.br>
Requires-Python: >=3.13
Requires-Dist: requests>=2.32.3
